Mohamad_ml_library/DecisionTree.py
Mohamad_ml_library/DecisionTreeRegressor.py
Mohamad_ml_library/LinearRegression.py
Mohamad_ml_library/MLP.py
Mohamad_ml_library/Perceptron.py
Mohamad_ml_library/PolynomialRegression.py
Mohamad_ml_library/SVM.py
Mohamad_ml_library/__init__.py
Mohamad_ml_library/activationfunctions.py
Mohamad_ml_library/costfunctions.py
Mohamad_ml_library/optimisers.py
Mohamad_ml_library-0.0.3.dist-info/LICENCE.txt
Mohamad_ml_library-0.0.3.dist-info/METADATA
Mohamad_ml_library-0.0.3.dist-info/WHEEL
Mohamad_ml_library-0.0.3.dist-info/top_level.txt
Mohamad_ml_library-0.0.3.dist-info/RECORD
